afterquote/__init__.py
afterquote/_market_calendar.py
afterquote/_security_pair.py
afterquote/_yfinance_wrapper.py
afterquote-0.2.1.dist-info/licenses/LICENSE
afterquote-0.2.1.dist-info/METADATA
afterquote-0.2.1.dist-info/WHEEL
afterquote-0.2.1.dist-info/top_level.txt
afterquote-0.2.1.dist-info/RECORD
