Metadata-Version: 2.4
Name: afterquote
Version: 0.2.1
Summary: Synthetic after-hours quote generator
Author-email: Mohammad Junaid <mohammadjunaiduk@gmail.com>
License-Expression: MIT
Requires-Python: >=3.8
License-File: LICENSE
Requires-Dist: yfinance
Requires-Dist: pandas
Requires-Dist: pytz
Requires-Dist: pandas_market_calendars
Provides-Extra: dev
Requires-Dist: black; extra == "dev"
Requires-Dist: pylint; extra == "dev"
Dynamic: license-file
